{
  "filename": "krig_p72_archimedes_emerald",
  "display_name": "Kruger P-72 Archimedes Emerald",
  "hull_hp": 1000,
  "armor": {
    "hp": 480,
    "resist_physical": 0.85,
    "resist_energy": 1.3,
    "resist_distortion": 1.0,
    "damage_mult_physical": 0.85,
    "damage_mult_energy": 0.7,
    "damage_mult_distortion": 1.0
  },
  "thrusters": {
    "main_hp": 0,
    "retro_hp": 0,
    "mav_hp": 0,
    "vtol_hp": 0,
    "total_hp": 54000
  },
  "components": {
    "turret_total_hp": 0,
    "powerplant_total_hp": 240,
    "cooler_total_hp": 360,
    "shield_gen_total_hp": 81,
    "qd_total_hp": 0,
    "thruster_total_hp": 54000
  },
  "shield_count": 1,
  "max_shield_size": 1,
  "default_shield_ref": "shld_yorm_s01_targa_scitem",
  "weapon_hardpoints": [
    {
      "port_name": "hardpoint_weapon_gun_left_wing",
      "max_size": 1,
      "gimbal_type": "Gimbal",
      "category": "pilot",
      "mount_name": "mount_gimbal_s1",
      "sub_ports": [
        {
          "size": 1,
          "default_weapon": "klwe_laserrepeater_s1"
        }
      ]
    },
    {
      "port_name": "hardpoint_weapon_gun_InnerLeft_wing",
      "max_size": 1,
      "gimbal_type": "Gimbal",
      "category": "pilot",
      "mount_name": "mount_gimbal_s1",
      "sub_ports": [
        {
          "size": 1,
          "default_weapon": "klwe_laserrepeater_s1"
        }
      ]
    },
    {
      "port_name": "hardpoint_weapon_gun_right_wing",
      "max_size": 1,
      "gimbal_type": "Gimbal",
      "category": "pilot",
      "mount_name": "mount_gimbal_s1",
      "sub_ports": [
        {
          "size": 1,
          "default_weapon": "klwe_laserrepeater_s1"
        }
      ]
    },
    {
      "port_name": "hardpoint_weapon_gun_InnerRight_wing",
      "max_size": 1,
      "gimbal_type": "Gimbal",
      "category": "pilot",
      "mount_name": "mount_gimbal_s1",
      "sub_ports": [
        {
          "size": 1,
          "default_weapon": "klwe_laserrepeater_s1"
        }
      ]
    }
  ],
  "cooler_total_hp": 360,
  "shield_gen_total_hp": 81,
  "thruster_total_hp": 54000
}